Vibrationology_Interactive_GUI_demo/__init__.py
Vibrationology_Interactive_GUI_demo/maindemo.py
Vibrationology_Interactive_GUI_demo/page1_n.py
Vibrationology_Interactive_GUI_demo/page2_n.py
Vibrationology_Interactive_GUI_demo/page3_n.py
Vibrationology_Interactive_GUI_demo/page4_n.py
Vibrationology_Interactive_GUI_demo/page_0.py
Vibrationology_Interactive_GUI_demo/page_1.py
Vibrationology_Interactive_GUI_demo/page_2.py
Vibrationology_Interactive_GUI_demo/page_3.py
Vibrationology_Interactive_GUI_demo/page_4.py
interactive_GUI-1.0.0.dist-info/METADATA
interactive_GUI-1.0.0.dist-info/WHEEL
interactive_GUI-1.0.0.dist-info/top_level.txt
interactive_GUI-1.0.0.dist-info/RECORD
