Metadata-Version: 2.1
Name: interactive_GUI
Version: 1.0.0
Summary: Description of my project
Author: LI XIANG XIAN FENG
Author-email: 1111111111@qq.com
License: MIT
Requires-Dist: matplotlib
Requires-Dist: numpy
Requires-Dist: scipy
Requires-Dist: vpython
